README.md
setup.cfg
setup.py
easy_exceptions/__init__.py
easy_exceptions/easy_exceptions.py
easy_exceptions.egg-info/PKG-INFO
easy_exceptions.egg-info/SOURCES.txt
easy_exceptions.egg-info/dependency_links.txt
easy_exceptions.egg-info/top_level.txt