Metadata-Version: 2.1
Name: easy-exceptions
Version: 1.0.2
Summary: Throw and catch named exceptions without creating a class first
Home-page: https://github.com/Cruuncher/EasyExceptions
Author: Patrick Robertshaw
Author-email: patrick.robertshaw1@gmail.com
License: MIT
Download-URL: https://github.com/Cruuncher/EasyExceptions/archive/1.0.2.tar.gz
Keywords: exceptions
Platform: UNKNOWN
Classifier: Development Status :: 5 - Production/Stable
Classifier: Intended Audience :: Developers
Classifier: Topic :: Software Development :: Build Tools
Classifier: License :: OSI Approved :: MIT License
Classifier: Programming Language :: Python :: 3
